registers/piso_shift_reg/piso_reg.v
module piso #(parameter width = 4)(input clk,rst,shift,load,
	input [width-1:0]parallel_in,output reg serial_out);
reg [width-1:0]shift_reg;
always@(posedge clk)begin
	if(rst)begin
		shift_reg <= {width{1'b0}};
		serial_out <= 1'b0;
	end
	else if(load)
		shift_reg <= parallel_in;
	else if(shift)begin
		serial_out <= shift_reg[0];
		shift_reg <= shift_reg >> 1;
	end
end	
endmodule

registers/piso_shift_reg/piso_reg_tb.v
module piso_tb;
reg clk,rst,shift,load;
reg [3:0]parallel_in;
wire serial_out;
piso #(.width(4)) piso_dut(.clk(clk),.rst(rst),.shift(shift),.load(load),.parallel_in(parallel_in),.serial_out(serial_out));
always #5 clk = ~clk;
initial begin
	$monitor("time = %0t|rst = %b|parallel_in = %b|serial_out = %b|",$time,rst,parallel_in,serial_out); 
	clk = 0;
	rst = 1;
	shift = 0;
	load = 1;
	parallel_in = 4'b0000;
	#10;
       	rst = 0;
	#10; 
	load = 1;
	parallel_in = 4'b1001;
	#10;
       	load = 0;
	shift = 1;
	#40;
       	shift = 0;
       #20 $finish;
end
initial begin 
	$dumpfile("piso.vcd");
	$dumpvars(0,piso_tb);
end
endmodule

registers/piso_shift_reg/piso.vcd
$date
	Sun Dec 28 17:05:09 2025
$end
$version
	Icarus Verilog
$end
$timescale
	1s
$end
$scope module piso_tb $end
$var wire 1 ! serial_out $end
$var reg 1 " clk $end
$var reg 1 # load $end
$var reg 4 $ parallel_in [3:0] $end
$var reg 1 % rst $end
$var reg 1 & shift $end
$scope module piso_dut $end
$var wire 1 " clk $end
$var wire 1 # load $end
$var wire 4 ' parallel_in [3:0] $end
$var wire 1 % rst $end
$var wire 1 & shift $end
$var parameter 32 ( width $end
$var reg 1 ! serial_out $end
$var reg 4 ) shift_reg [3:0] $end
$upscope $end
$upscope $end
$enddefinitions $end
$comment Show the parameter values. $end
$dumpall
b100 (
$end
#0
$dumpvars
bx )
b0 '
0&
1%
b0 $
1#
0"
x!
$end
#5
0!
b0 )
1"
#10
0"
0%
#15
1"
#20
0"
b1001 $
b1001 '
#25
b1001 )
1"
#30
0"
1&
0#
#35
b100 )
1!
1"
#40
0"
#45
b10 )
0!
1"
#50
0"
#55
b1 )
1"
#60
0"
#65
b0 )
1!
1"
#70
0"
0&
