sync_counter/ud_counter/ud_counter.v
module ud_count(input clk,rst,up_down,
	output reg [3:0]count);

always@(posedge clk)begin
	if(rst)
		count <= 4'b0000;
	else if(up_down)
		count <= count + 1;
	else
		count <= count - 1;
end

endmodule

sync_counter/ud_counter/ud_counter_tb.v
module ud_count_tb;
reg clk,rst,up_down;
wire [3:0]count;

ud_count ud_count_dut(.clk(clk),.rst(rst),.up_down(up_down),.count(count));

always #5 clk = ~clk;

initial begin 
	clk = 0;
	rst = 1;
	up_down = 0;
	
	$monitor("time = %0t|rst = %b|up_down = %b|count = %b",$time,rst,up_down,count);
	#10;
	rst = 0;
	up_down = 1;
	#155;
	up_down = 0;
	#155;
	$finish;
end
initial begin
	$dumpfile("ud_count.vcd");
	$dumpvars(0,ud_count_tb);
end

endmodule

sync_counter/ud_counter/ud_count.vcd
$date
	Tue Dec 30 10:39:16 2025
$end
$version
	Icarus Verilog
$end
$timescale
	1s
$end
$scope module ud_count_tb $end
$var wire 4 ! count [3:0] $end
$var reg 1 " clk $end
$var reg 1 # rst $end
$var reg 1 $ up_down $end
$scope module ud_count_dut $end
$var wire 1 " clk $end
$var wire 1 # rst $end
$var wire 1 $ up_down $end
$var reg 4 % count [3:0] $end
$upscope $end
$upscope $end
$enddefinitions $end
$comment Show the parameter values. $end
$dumpall
$end
#0
$dumpvars
bx %
0$
1#
0"
bx !
$end
#5
b0 !
b0 %
1"
#10
0"
1$
0#
#15
b1 !
b1 %
1"
#20
0"
#25
b10 !
b10 %
1"
#30
0"
#35
b11 !
b11 %
1"
#40
0"
#45
b100 !
b100 %
1"
#50
0"
#55
b101 !
b101 %
1"
#60
0"
#65
b110 !
b110 %
1"
#70
0"
#75
b111 !
b111 %
1"
#80
0"
#85
b1000 !
b1000 %
1"
#90
0"
#95
b1001 !
b1001 %
1"
#100
0"
#105
b1010 !
b1010 %
1"
#110
0"
#115
b1011 !
b1011 %
1"
#120
0"
#125
b1100 !
b1100 %
1"
#130
0"
#135
b1101 !
b1101 %
1"
#140
0"
#145
b1110 !
b1110 %
1"
#150
0"
#155
b1111 !
b1111 %
1"
#160
0"
#165
b1110 !
b1110 %
1"
0$
#170
0"
#175
b1101 !
b1101 %
1"
#180
0"
#185
b1100 !
b1100 %
1"
#190
0"
#195
b1011 !
b1011 %
1"
#200
0"
#205
b1010 !
b1010 %
1"
#210
0"
#215
b1001 !
b1001 %
1"
#220
0"
#225
b1000 !
b1000 %
1"
#230
0"
#235
b111 !
b111 %
1"
#240
0"
#245
b110 !
b110 %
1"
#250
0"
#255
b101 !
b101 %
1"
#260
0"
#265
b100 !
b100 %
1"
#270
0"
#275
b11 !
b11 %
1"
#280
0"
#285
b10 !
b10 %
1"
#290
0"
#295
b1 !
b1 %
1"
#300
0"
#305
b0 !
b0 %
1"
#310
0"
#315
b1111 !
b1111 %
1"
