sequence_detector/moore_seq_det/non-overlapping/1010_sequence/1010_seq.v
module seq_1010(input wire clk,rst,x,output reg z);
parameter s0 = 3'd0,
	s1 = 3'd1,
	s2 = 3'd2,
	s3 = 3'd3,
	s4 = 3'd4;
reg[2:0] present_state,  next_state;
always@(posedge clk or posedge rst)begin
	if(rst)begin
		present_state <= s0;
	end
	else present_state <= next_state;
end
always@(*)begin
	case(present_state)

		s0 : next_state  = (x)? s1 : s0;
		s1 : next_state  = (x)? s1 : s2;
		s2 : next_state  = (x)? s3 : s0;
		s3 : next_state  = (x)? s1 : s4;
		s4 : next_state  = (x)? s1 : s0;
		default:next_state = s0;
	endcase
end
always@(*)begin
	z = (present_state == s4);
end
endmodule

sequence_detector/moore_seq_det/non-overlapping/1010_sequence/1010_seq_tb.v
module seq_1010_tb;
reg clk,rst,x;
wire z;
seq_1010 dut(
	.clk(clk),
	.rst(rst),
	.x(x),
	.z(z)
);
initial clk = 0;
always #5 clk = ~clk;
initial begin
	$monitor("rst = %0b | x = %0b | z = %0b",rst,x,z);
	rst = 1;
	x  = 0;
	#12 rst = 0;
	#7 x = 1;
	#10 x = 0;
	#10 x = 1;
	#10 x = 0;
	#10 x = 1;
	#10 x = 0;
	#10 x = 1;
	#10 x = 0;
	#10 x = 1;
	#20 x = 0;
	#20;
	$finish;
end
initial begin
	$dumpfile("seq_1010.vcd");
	$dumpvars(0,seq_1010_tb);
end

endmodule

sequence_detector/moore_seq_det/non-overlapping/1010_sequence/seq_1010.vcd
$date
	Sat Jan  3 14:01:56 2026
$end
$version
	Icarus Verilog
$end
$timescale
	1s
$end
$scope module seq_1010_tb $end
$var wire 1 ! z $end
$var reg 1 " clk $end
$var reg 1 # rst $end
$var reg 1 $ x $end
$scope module dut $end
$var wire 1 " clk $end
$var wire 1 # rst $end
$var wire 1 $ x $end
$var parameter 3 % s0 $end
$var parameter 3 & s1 $end
$var parameter 3 ' s2 $end
$var parameter 3 ( s3 $end
$var parameter 3 ) s4 $end
$var reg 3 * next_state [2:0] $end
$var reg 3 + present_state [2:0] $end
$var reg 1 ! z $end
$upscope $end
$upscope $end
$enddefinitions $end
$comment Show the parameter values. $end
$dumpall
b100 )
b11 (
b10 '
b1 &
b0 %
$end
#0
$dumpvars
b0 +
b0 *
0$
1#
0"
0!
$end
#5
1"
#10
0"
#12
0#
#15
1"
#19
b1 *
1$
#20
0"
#25
b1 +
1"
#29
b10 *
0$
#30
0"
#35
b0 *
b10 +
1"
#39
b11 *
1$
#40
0"
#45
b1 *
b11 +
1"
#49
b100 *
0$
#50
0"
#55
1!
b0 *
b100 +
1"
#59
b1 *
1$
#60
0"
#65
0!
b1 +
1"
#69
b10 *
0$
#70
0"
#75
b0 *
b10 +
1"
#79
b11 *
1$
#80
0"
#85
b1 *
b11 +
1"
#89
b100 *
0$
#90
0"
#95
1!
b0 *
b100 +
1"
#99
b1 *
1$
#100
0"
#105
0!
b1 +
1"
#110
0"
#115
1"
#119
b10 *
0$
#120
0"
#125
b0 *
b10 +
1"
#130
0"
#135
b0 +
1"
