sync_counter/down_counter/down_counter.v
module down_count(input clk,rst,output reg[3:0] count);

always@(posedge clk)begin
	if(rst)
		count <= 4'b1111;
	else
		count <= count - 1;
end

endmodule

sync_counter/down_counter/down_counter_tb.v
module down_count_tb;
reg clk,rst;
wire [3:0]count;

down_count d_count_dut(.clk(clk),.rst(rst),.count(count));

always #5 clk = ~clk;

initial begin 
	clk = 0;
	rst = 1;
	
	$monitor("time = %0t | rst = %b | count = %b",$time,rst,count);
	#10;
	rst = 0;
	#200;
	$finish;
end
initial begin
	$dumpfile("down_counter.vcd");
	$dumpvars(0,down_count_tb);
end
endmodule

sync_counter/down_counter/down_counter.vcd
$date
	Tue Dec 30 08:33:22 2025
$end
$version
	Icarus Verilog
$end
$timescale
	1s
$end
$scope module down_count_tb $end
$var wire 4 ! count [3:0] $end
$var reg 1 " clk $end
$var reg 1 # rst $end
$scope module d_count_dut $end
$var wire 1 " clk $end
$var wire 1 # rst $end
$var reg 4 $ count [3:0] $end
$upscope $end
$upscope $end
$enddefinitions $end
$comment Show the parameter values. $end
$dumpall
$end
#0
$dumpvars
bx $
1#
0"
bx !
$end
#5
b1111 !
b1111 $
1"
#10
0"
0#
#15
b1110 !
b1110 $
1"
#20
0"
#25
b1101 !
b1101 $
1"
#30
0"
#35
b1100 !
b1100 $
1"
#40
0"
#45
b1011 !
b1011 $
1"
#50
0"
#55
b1010 !
b1010 $
1"
#60
0"
#65
b1001 !
b1001 $
1"
#70
0"
#75
b1000 !
b1000 $
1"
#80
0"
#85
b111 !
b111 $
1"
#90
0"
#95
b110 !
b110 $
1"
#100
0"
#105
b101 !
b101 $
1"
#110
0"
#115
b100 !
b100 $
1"
#120
0"
#125
b11 !
b11 $
1"
#130
0"
#135
b10 !
b10 $
1"
#140
0"
#145
b1 !
b1 $
1"
#150
0"
#155
b0 !
b0 $
1"
#160
0"
#165
b1111 !
b1111 $
1"
#170
0"
#175
b1110 !
b1110 $
1"
#180
0"
#185
b1101 !
b1101 $
1"
#190
0"
#195
b1100 !
b1100 $
1"
#200
0"
#205
b1011 !
b1011 $
1"
