registers/pipo_reg/pipo_reg.v
module pipo(input clk,rst,load,
	input [3:0] parallel_in,output [3:0]parallel_out);
reg[3:0]pipo_reg;
always@(posedge clk)begin
	if(rst)begin
		pipo_reg <= 4'b0000;
	end
	else if(load)begin
		pipo_reg <= parallel_in;
	end
end
assign parallel_out = pipo_reg;
endmodule

registers/pipo_reg/pipo_reg_tb.v
module pipo_tb;
reg clk,rst,load;
reg [3:0] parallel_in;
wire [3:0] parallel_out;
pipo pipo_dut(.clk(clk),.rst(rst),.load(load),.parallel_in(parallel_in),.parallel_out(parallel_out));
always #5 clk = ~clk;
initial begin
	$monitor("time = %0t | rst = %b | parallel_in = %b | parallel_out = %b",$time,rst,parallel_in,parallel_out);
	clk = 0;
	rst = 1;
	load = 0;
	parallel_in = 4'b0000;
	#10;
	rst = 0;
	#10;
	load = 1;
	parallel_in = 4'b1001;
	#10;
	load = 0;
	#10;
	load = 1;
	parallel_in = 4'b1101;
	#10;
	load = 0;
	#20 $finish;
end
initial begin
	$dumpfile("pipo.vcd");
	$dumpvars(0,pipo_tb);
end
endmodule

registers/pipo_reg/pipo.vcd
$date
	Mon Dec 29 08:44:50 2025
$end
$version
	Icarus Verilog
$end
$timescale
	1s
$end
$scope module pipo_tb $end
$var wire 4 ! parallel_out [3:0] $end
$var reg 1 " clk $end
$var reg 1 # load $end
$var reg 4 $ parallel_in [3:0] $end
$var reg 1 % rst $end
$scope module pipo_dut $end
$var wire 1 " clk $end
$var wire 1 # load $end
$var wire 4 & parallel_in [3:0] $end
$var wire 4 ' parallel_out [3:0] $end
$var wire 1 % rst $end
$var reg 4 ( pipo_reg [3:0] $end
$upscope $end
$upscope $end
$enddefinitions $end
$comment Show the parameter values. $end
$dumpall
$end
#0
$dumpvars
bx (
bx '
b0 &
1%
b0 $
0#
0"
bx !
$end
#5
b0 !
b0 '
b0 (
1"
#10
0"
0%
#15
1"
#20
0"
b1001 $
b1001 &
1#
#25
b1001 !
b1001 '
b1001 (
1"
#30
0"
0#
#35
1"
#40
0"
b1101 $
b1101 &
1#
#45
b1101 !
b1101 '
b1101 (
1"
#50
0"
0#
