sync_counter/mod_n_counter/mod_n_counter.v
module mod_n_count #(parameter n = 10,width = 4)(input clk,rst,
	output reg[width-1:0]count);

always@(posedge clk)begin
	if(rst)
		count <= 0;
	else if(count == n - 1)
		count <= 0;
	else
		count <= count + 1;
end

endmodule

sync_counter/mod_n_counter/mod_n_counter_tb.v
module mod_n_count_tb;
reg clk,rst;
wire [3:0] count;

mod_n_count #(.n(10),.width(4)) mod_n_count_dut(.clk(clk),.rst(rst),.count(count));

always #5 clk = ~clk;

initial begin
	clk = 0;
	rst = 1;
	
	$monitor("time = %0t|rst = %b|count = %b|",$time,rst,count);

	#10;
	rst = 0;
	#110;
	$finish;
end
initial begin 
	$dumpfile("mod_n_counter.vcd");
	$dumpvars(0,mod_n_count_tb);
end
endmodule

sync_counter/mod_n_counter/mod_n_counter.vcd
$date
	Tue Dec 30 11:35:17 2025
$end
$version
	Icarus Verilog
$end
$timescale
	1s
$end
$scope module mod_n_count_tb $end
$var wire 4 ! count [3:0] $end
$var reg 1 " clk $end
$var reg 1 # rst $end
$scope module mod_n_count_dut $end
$var wire 1 " clk $end
$var wire 1 # rst $end
$var parameter 32 $ n $end
$var parameter 32 % width $end
$var reg 4 & count [3:0] $end
$upscope $end
$upscope $end
$enddefinitions $end
$comment Show the parameter values. $end
$dumpall
b100 %
b1010 $
$end
#0
$dumpvars
bx &
1#
0"
bx !
$end
#5
b0 !
b0 &
1"
#10
0"
0#
#15
b1 !
b1 &
1"
#20
0"
#25
b10 !
b10 &
1"
#30
0"
#35
b11 !
b11 &
1"
#40
0"
#45
b100 !
b100 &
1"
#50
0"
#55
b101 !
b101 &
1"
#60
0"
#65
b110 !
b110 &
1"
#70
0"
#75
b111 !
b111 &
1"
#80
0"
#85
b1000 !
b1000 &
1"
#90
0"
#95
b1001 !
b1001 &
1"
#100
0"
#105
b0 !
b0 &
1"
#110
0"
#115
b1 !
b1 &
1"
