async_counter/up_counter/up_counter.v
module up_count(input clk,rst,output reg[3:0]q);
always@(posedge clk or posedge rst)begin
	if(rst)
		q[0] <= 0;
	else
		q[0] <= ~q[0];
end
always@(posedge ~q[0] or posedge rst)begin
	if(rst)
		q[1] <= 0;
	else
		q[1] <= ~q[1];
end
always@(posedge ~q[1] or posedge rst)begin
	if(rst)
		q[2] <= 0;
	else
		q[2] <= ~q[2];
end
always@(posedge ~q[2] or posedge rst)begin
	if(rst)
		q[3] <= 0;
	else 
		q[3] <= ~q[3];
end

endmodule

async_counter/up_counter/up_counter_tb.v
module up_count_tb;
reg clk,rst;
wire [3:0] count;
up_count up_dut(.clk(clk),.rst(rst),.q(count));
always #5 clk = ~clk;
initial begin
	clk = 0;
	rst = 1;
	$monitor("time = %0t|clk = %b|rst = %b|count = %b|",$time,clk,rst,count);
	#10 rst = 0;
	#155;
	$finish;
end
initial begin
	$dumpfile("up_count.vcd");
	$dumpvars(0,up_count_tb);
end

endmodule

async_counter/down_counter/up_count.vcd
$date
	Sat Jan  3 07:26:27 2026
$end
$version
	Icarus Verilog
$end
$timescale
	1s
$end
$scope module up_count_tb $end
$var wire 4 ! count [3:0] $end
$var reg 1 " clk $end
$var reg 1 # rst $end
$scope module up_dut $end
$var wire 1 " clk $end
$var wire 1 # rst $end
$var reg 4 $ q [3:0] $end
$upscope $end
$upscope $end
$enddefinitions $end
$comment Show the parameter values. $end
$dumpall
$end
#0
$dumpvars
b1111 $
1#
0"
b1111 !
$end
#5
1"
#10
0"
0#
#15
b1110 !
b1110 $
1"
#20
0"
#25
b1101 !
b1101 $
1"
#30
0"
#35
b1100 !
b1100 $
1"
#40
0"
#45
b1011 !
b1011 $
1"
#50
0"
#55
b1010 !
b1010 $
1"
#60
0"
#65
b1001 !
b1001 $
1"
#70
0"
#75
b1000 !
b1000 $
1"
#80
0"
#85
b111 !
b111 $
1"
#90
0"
#95
b110 !
b110 $
1"
#100
0"
#105
b101 !
b101 $
1"
#110
0"
#115
b100 !
b100 $
1"
#120
0"
#125
b11 !
b11 $
1"
#130
0"
#135
b10 !
b10 $
1"
#140
0"
#145
b1 !
b1 $
1"
#150
0"
#155
b0 !
b0 $
1"
#160
0"
#165
b1111 !
b1111 $
1"
