registers/universal_shift_reg/universal_reg.v
module uni_reg(input clk,rst,shift_r_in,shift_l_in,
	input [1:0]sel,input[3:0]parallel_in,output reg[3:0]parallel_out);
always@(posedge clk)begin
	if(rst)begin
		parallel_out <= 4'b0000;
	end
	else begin
		case(sel)
			2'b00 : parallel_out <= parallel_out;
			2'b01 : parallel_out <= {shift_r_in,parallel_out[3:1]};
			2'b10 : parallel_out <= {parallel_out[2:0],shift_l_in};
			2'b11 : parallel_out <= parallel_in;
		endcase
	end
end
endmodule

registers/universal_shift_reg/universal_reg_tb.v
module uni_reg_tb;
reg clk,rst,shift_r_in,shift_l_in;
reg [1:0] sel;
reg [3:0] parallel_in;
wire [3:0] parallel_out;
uni_reg uni_reg_dut(.clk(clk),.rst(rst),.shift_r_in(shift_r_in),.shift_l_in(shift_l_in),.sel(sel),.parallel_in(parallel_in),.parallel_out(parallel_out));
always #5 clk = ~clk;
initial begin
	clk = 0;
	rst = 1;
	shift_r_in = 0;
	shift_l_in = 0;
	parallel_in = 4'b0000;
	sel = 2'b00;
	$monitor("time = %0t|rst = %b|shift_r_in = %b|shift_l_in = %b|parallel_in = %b|parallel_out = %b",$time,rst,shift_r_in,shift_l_in,parallel_in,parallel_out);
	#10;
	rst = 0;
	#10;
	sel = 2'b11;
	parallel_in = 4'b1001;
	#10;
	sel = 2'b00;
	#10;
	sel = 2'b01;
	shift_r_in = 1;
	#10;
	shift_r_in = 0;
	#10;
	sel = 2'b10;
	shift_l_in = 1;
	#10;
	shift_l_in = 0;
	#10;
	sel = 2'b00;
	#20 $finish;
end
initial begin
	$dumpfile("uni_reg.vcd");
	$dumpvars(0,uni_reg_tb);
end



endmodule

registers/universal_shift_reg/uni_reg.vcd
$date
	Tue Dec 30 04:18:50 2025
$end
$version
	Icarus Verilog
$end
$timescale
	1s
$end
$scope module uni_reg_tb $end
$var wire 4 ! parallel_out [3:0] $end
$var reg 1 " clk $end
$var reg 4 # parallel_in [3:0] $end
$var reg 1 $ rst $end
$var reg 2 % sel [1:0] $end
$var reg 1 & shift_l_in $end
$var reg 1 ' shift_r_in $end
$scope module uni_reg_dut $end
$var wire 1 " clk $end
$var wire 4 ( parallel_in [3:0] $end
$var wire 1 $ rst $end
$var wire 2 ) sel [1:0] $end
$var wire 1 & shift_l_in $end
$var wire 1 ' shift_r_in $end
$var reg 4 * parallel_out [3:0] $end
$upscope $end
$upscope $end
$enddefinitions $end
$comment Show the parameter values. $end
$dumpall
$end
#0
$dumpvars
bx *
b0 )
b0 (
0'
0&
b0 %
1$
b0 #
0"
bx !
$end
#5
b0 !
b0 *
1"
#10
0"
0$
#15
1"
#20
0"
b1001 #
b1001 (
b11 %
b11 )
#25
b1001 !
b1001 *
1"
#30
0"
b0 %
b0 )
#35
1"
#40
0"
1'
b1 %
b1 )
#45
b1100 !
b1100 *
1"
#50
0"
0'
#55
b110 !
b110 *
1"
#60
0"
1&
b10 %
b10 )
#65
b1101 !
b1101 *
1"
#70
0"
0&
#75
b1010 !
b1010 *
1"
#80
0"
b0 %
b0 )
