registers/siso_shift_reg/siso_reg.v
module siso #(parameter width = 4)(input clk,rst,serial_in,output serial_out);
reg [width-1:0]shift_reg;
always@(posedge clk)begin
	if(rst)
		shift_reg <= {width{1'b0}};
	else
		shift_reg <= {serial_in,shift_reg[width-1:1]};
end
assign serial_out = shift_reg[0];
endmodule

registers/siso_shift_reg/siso_reg_tb.v
module siso_tb;
reg clk,rst,serial_in;
wire serial_out;
siso #(.width(4)) siso_dut(.clk(clk),.rst(rst),.serial_in(serial_in),.serial_out(serial_out));
always #5 clk = ~clk;
initial begin
	$monitor("time = %0t | rst = %b | serial_in = %b | serial_out = %b",$time,rst,serial_in,serial_out);
	clk = 0;
	rst = 1;
	serial_in = 0;
	#10 rst = 0;
	#10 serial_in = 1;
	#10 serial_in = 0;
	#10 serial_in = 0;
	#10 serial_in = 1;
	#30 $finish;
end
initial begin
	$dumpfile("siso.vcd");
	$dumpvars(0,siso_tb);
end
endmodule

registers/siso_shift_reg/siso.vcd
$date
	Sat Dec 27 15:33:31 2025
$end
$version
	Icarus Verilog
$end
$timescale
	1s
$end
$scope module siso_tb $end
$var wire 1 ! serial_out $end
$var reg 1 " clk $end
$var reg 1 # rst $end
$var reg 1 $ serial_in $end
$scope module siso_dut $end
$var wire 1 " clk $end
$var wire 1 # rst $end
$var wire 1 $ serial_in $end
$var wire 1 ! serial_out $end
$var parameter 32 % width $end
$var reg 4 & shift_reg [3:0] $end
$upscope $end
$upscope $end
$enddefinitions $end
$comment Show the parameter values. $end
$dumpall
b100 %
$end
#0
$dumpvars
bx &
0$
1#
0"
x!
$end
#5
0!
b0 &
1"
#10
0"
0#
#15
1"
#20
0"
#25
b1000 &
1"
1$
#30
0"
#35
b100 &
1"
0$
#40
0"
#45
b10 &
1"
#50
0"
#55
1!
b1 &
1"
#60
0"
1$
#65
0!
b1000 &
1"
#70
0"
#75
b1100 &
1"
#80
0"
#85
b1110 &
1"
#90
0"
#95
1!
b1111 &
1"
